spakky/plugins/kafka/__init__.py
spakky/plugins/kafka/common/__init__.py
spakky/plugins/kafka/common/config.py
spakky/plugins/kafka/common/constants.py
spakky/plugins/kafka/event/__init__.py
spakky/plugins/kafka/event/consumer.py
spakky/plugins/kafka/event/publisher.py
spakky/plugins/kafka/main.py
spakky/plugins/kafka/post_processor.py
spakky/plugins/kafka/py.typed
spakky_kafka-5.0.1.dist-info/WHEEL
spakky_kafka-5.0.1.dist-info/entry_points.txt
spakky_kafka-5.0.1.dist-info/METADATA
spakky_kafka-5.0.1.dist-info/RECORD
