Metadata-Version: 2.3
Name: spakky-kafka
Version: 5.0.1
Summary: Apache Kafka plugin for Spakky framework
Author: Spakky
Author-email: Spakky <sejong418@icloud.com>
License: MIT
Requires-Dist: confluent-kafka>=2.12.2
Requires-Dist: pydantic>=2.12.5
Requires-Dist: pydantic-settings>=2.12.0
Requires-Dist: spakky-event>=5.0.1
Requires-Python: >=3.11
